{
  "frames": {
    "grass_0.png": {
      "frame": {
        "x": 0,
        "y": 0,
        "w": 32,
        "h": 32
      },
      "rotated": false,
      "trimmed": false,
      "spriteSourceSize": {
        "x": 0,
        "y": 0,
        "w": 32,
        "h": 32
      },
      "sourceSize": {
        "w": 32,
        "h": 32
      }
    },
    "tree_0.png": {
      "frame": {
        "x": 32,
        "y": 0,
        "w": 32,
        "h": 32
      },
      "rotated": false,
      "trimmed": false,
      "spriteSourceSize": {
        "x": 0,
        "y": 0,
        "w": 32,
        "h": 32
      },
      "sourceSize": {
        "w": 32,
        "h": 32
      }
    },
    "tree_1.png": {
      "frame": {
        "x": 64,
        "y": 0,
        "w": 32,
        "h": 32
      },
      "rotated": false,
      "trimmed": false,
      "spriteSourceSize": {
        "x": 0,
        "y": 0,
        "w": 32,
        "h": 32
      },
      "sourceSize": {
        "w": 32,
        "h": 32
      }
    },
    "tree_3.png": {
      "frame": {
        "x": 96,
        "y": 0,
        "w": 32,
        "h": 32
      },
      "rotated": false,
      "trimmed": false,
      "spriteSourceSize": {
        "x": 0,
        "y": 0,
        "w": 32,
        "h": 32
      },
      "sourceSize": {
        "w": 32,
        "h": 32
      }
    },
    "trees_2.png": {
      "frame": {
        "x": 128,
        "y": 0,
        "w": 32,
        "h": 32
      },
      "rotated": false,
      "trimmed": false,
      "spriteSourceSize": {
        "x": 0,
        "y": 0,
        "w": 32,
        "h": 32
      },
      "sourceSize": {
        "w": 32,
        "h": 32
      }
    },
    "water_0.png": {
      "frame": {
        "x": 160,
        "y": 0,
        "w": 32,
        "h": 32
      },
      "rotated": false,
      "trimmed": false,
      "spriteSourceSize": {
        "x": 0,
        "y": 0,
        "w": 32,
        "h": 32
      },
      "sourceSize": {
        "w": 32,
        "h": 32
      }
    }
  },
  "meta": {
    "app": "https://www.codeandweb.com/texturepacker",
    "version": "1.0",
    "image": "map.png",
    "format": "RGBA8888",
    "size": {
      "w": 192,
      "h": 32
    },
    "scale": "1",
    "smartupdate": "$TexturePacker:SmartUpdate:1674426a707e55a84ec7ed7411bea8ff:aadb1f3663ca7ae063b44c63dffd88f2:68463c66230aaeb26021edb8ea8cd9b6$"
  }
}
